wirehead/__init__.py
wirehead/dataset.py
wirehead/generator.py
wirehead-0.9.1.dist-info/LICENSE
wirehead-0.9.1.dist-info/METADATA
wirehead-0.9.1.dist-info/WHEEL
wirehead-0.9.1.dist-info/top_level.txt
wirehead-0.9.1.dist-info/RECORD
