Metadata-Version: 2.2
Name: wirehead
Version: 0.9.1
Summary: Caching system for scaling of synthetic data generators using MongoDB
Home-page: https://github.com/neuroneural/wirehead
Author: Neuroneural Lab
Author-email: mdoan4@gsu.edu
Classifier: Development Status :: 4 - Beta
Classifier: Intended Audience :: Science/Research
Classifier: License :: OSI Approved :: MIT License
Classifier: Programming Language :: Python :: 3
Classifier: Topic :: Scientific/Engineering :: Artificial Intelligence
Requires-Python: >=3.6
License-File: LICENSE
Requires-Dist: pymongo
Requires-Dist: torch
Requires-Dist: numpy
Requires-Dist: PyYaml
Dynamic: author
Dynamic: author-email
Dynamic: classifier
Dynamic: description
Dynamic: description-content-type
Dynamic: home-page
Dynamic: requires-dist
Dynamic: requires-python
Dynamic: summary
